selenium_requests_html-1.0.dist-info/DESCRIPTION.rst
selenium_requests_html-1.0.dist-info/METADATA
selenium_requests_html-1.0.dist-info/RECORD
selenium_requests_html-1.0.dist-info/WHEEL
selenium_requests_html-1.0.dist-info/metadata.json
selenium_requests_html-1.0.dist-info/top_level.txt
seleniumrequestshtml/__init__.py
seleniumrequestshtml/request.py
