Metadata-Version: 2.0
Name: selenium-requests-html
Version: 1.0
Summary: Fork of selenium-requests that extends Selenium WebDriver classes to include the functionality from the Requests-HTML library, while doing all the needed cookie and request headers handling. Credit for most of what makes this work goes toto Chris Braun and his original work done on Selenium-Requestshttps://github.com/cryzed/Selenium-Requests
Home-page: https://github.com/illsea/Selenium-Requests-HTML
Author: Sylas Aldridge
Author-email: sylas@illsea.com
License: MIT
Platform: UNKNOWN
Classifier: Development Status :: 5 - Production/Stable
Classifier: Intended Audience :: Developers
Classifier: Natural Language :: English
Classifier: License :: OSI Approved :: MIT License
Classifier: Programming Language :: Python
Classifier: Programming Language :: Python :: 3
Requires-Python: >=3.6
Requires-Dist: requests
Requires-Dist: selenium
Requires-Dist: six
Requires-Dist: tldextract
